{
  "description": "Castling both sides: 1. e4 e5 2. Nf3 Nc6 3. Bc4 Bc5 4. O-O",
  "inputText": "1. e4 e5 2. Nf3 Nc6 3. Bc4 Bc5 4. O-O",
  "expectedMainline": [
    {
      "san": "e4",
      "from": "e2",
      "to": "e4",
      "fenFields123": "rnbqkbnr/pppppppp/8/8/4P3/8/PPPP1PPP/RNBQKBNR b KQkq",
      "moveNumber": 1,
      "color": "white"
    },
    {
      "san": "e5",
      "from": "e7",
      "to": "e5",
      "fenFields123": "rnbqkbnr/pppp1ppp/8/4p3/4P3/8/PPPP1PPP/RNBQKBNR w KQkq",
      "moveNumber": 1,
      "color": "black"
    },
    {
      "san": "Nf3",
      "from": "g1",
      "to": "f3",
      "fenFields123": "rnbqkbnr/pppp1ppp/8/4p3/4P3/5N2/PPPP1PPP/RNBQKB1R b KQkq",
      "moveNumber": 2,
      "color": "white"
    },
    {
      "san": "Nc6",
      "from": "b8",
      "to": "c6",
      "fenFields123": "r1bqkbnr/pppp1ppp/2n5/4p3/4P3/5N2/PPPP1PPP/RNBQKB1R w KQkq",
      "moveNumber": 2,
      "color": "black"
    },
    {
      "san": "Bc4",
      "from": "f1",
      "to": "c4",
      "fenFields123": "r1bqkbnr/pppp1ppp/2n5/4p3/2B1P3/5N2/PPPP1PPP/RNBQK2R b KQkq",
      "moveNumber": 3,
      "color": "white"
    },
    {
      "san": "Bc5",
      "from": "f8",
      "to": "c5",
      "fenFields123": "r1bqk1nr/pppp1ppp/2n5/2b1p3/2B1P3/5N2/PPPP1PPP/RNBQK2R w KQkq",
      "moveNumber": 3,
      "color": "black"
    },
    {
      "san": "O-O",
      "from": "e1",
      "to": "g1",
      "fenFields123": "r1bqk1nr/pppp1ppp/2n5/2b1p3/2B1P3/5N2/PPPP1PPP/RNBQ1RK1 b kq",
      "moveNumber": 4,
      "color": "white"
    }
  ]
}
